.coveragerc
.editorconfig
.gitignore
.travis.yml
LICENSE
README.md
pyproject.toml
requirements.txt
requirements_dev.txt
setup.cfg
setup.py
.github/workflows/python-publish.yml
democritus_asns/__init__.py
democritus_asns/asns.py
democritus_asns/asns_temp_utils.py
democritus_asns.egg-info/PKG-INFO
democritus_asns.egg-info/SOURCES.txt
democritus_asns.egg-info/dependency_links.txt
democritus_asns.egg-info/requires.txt
democritus_asns.egg-info/top_level.txt
democritus_asns.egg-info/zip-safe
tests/__init__.py
tests/test_asns.py